my_project/__init__.py
my_project/perp.py
my_project/product.py
my_project/trader.py
python_perp_sdk-0.0.1.dist-info/LICENSE
python_perp_sdk-0.0.1.dist-info/METADATA
python_perp_sdk-0.0.1.dist-info/WHEEL
python_perp_sdk-0.0.1.dist-info/top_level.txt
python_perp_sdk-0.0.1.dist-info/RECORD
