Metadata-Version: 2.1
Name: python-perp-sdk
Version: 0.0.1
Summary: Perp python sdk
Home-page: https://github.com/yourusername/my-python-sdk
Author: Author Name
Author-email: author@gmail.com
License-File: LICENSE
